Workbook

Sheet Main
B2: "Robux": one-time purchases or monthly subscriptions | I2: Price | J2: 131 | L2: Assets | N2: 6168 | O2: 7175 | Q2: EBIT | R2: =Model!J12/1.1 -> -553.04819 | S2: =R2/$J$7 -> -0.0064298331
A3: Revenue Recognition | I3: Shares | J3: =(618997327+48302658)/1000000 -> 667.29998 | L3: Liabilities | N3: 6099 | O3: 6966 | Q3: eEBIT | R3: =Model!R12/(1.1^9) -> 2779.9574 | S3: =R3/$J$7 -> 0.032320261
B4: Consumables virtual items: once consumed (10%) | I4: MC | J4: =J2*J3 -> 87416.298 | L4: Equity | N4: =N2-N3 -> 69 | O4: =O2-O3 -> 209 | Q4: Delta | R4: =(Model!I12-Model!F12)/3 -> 18.837681
B5: Durable virtual items: across avg lifetime and PU (90%) | I5: Cash | J5: =711.6+1697.86 -> 2409.46 | L5: CA | N5: 3275 | O5: 3728 | Q5: CX | R5: =AVERAGE(M12:O12)*-1 -> 1372.6967 | S5: =R4/R5 -> 0.01372312
I6: Debt | J6: =(1006) -> 1006 | L6: CL | N6: 3052 | O6: 3663
B7: deffered revenue and cost from durables? | I7: EV | J7: =J4+J6-J5 -> 86012.838 | L7: PPE | N7: 695 | O7: 659.5
J8: =J7/O11 -> 104.60031 | L8: ROU | N8: 665 | O8: 665.8
C9: 2021 | D9: 2022 | E9: =D9+1 -> 2023 | F9: =E9+1 -> 2024 | L9: INV | N9: 1043 | O9: 1610
B10: ePU life | C10: 23 | D10: 25 | E10: 28 | F10: 27 | G10: (months)
F11: =AVERAGE(C10:F10) -> 25.75 | G11: =F11/12 -> 2.1458333 | H11: (years) | L11: CFFO | M11: 369.29 | N11: 458.18 | O11: 822.3
B12: COGS: 3rd party payment processing fees | L12: CX | M12: -441 | N12: -2825.09 | O12: -852
L13: FCF | M13: =M11+M12 -> -71.71 | N13: =N11+N12 -> -2366.91 | O13: =O11+O12 -> -29.7
C14: 2022 | D14: =C14+1 -> 2023 | E14: =D14+1 -> 2024 | F14: 2034
B15: NA | C15: 1465.9 | D15: 1803.8 | E15: 2281.3 | F15: =E15*(1+M28) -> 8262.1326 | L15: ROTA | N15: =N11/SUM(N7:N8) -> 0.33689706 | O15: =O11/SUM(O7:O8) -> 0.62046329 | Q15: scale
B16: Europe | C16: 404.4 | D16: 505.6 | E16: 659.59 | F16: =E16*(1+M29) -> 2322.8522 | L16: D/E | N16: =N3/N4 -> 88.391304 | O16: =O3/O4 -> 33.330144
B17: APAC | C17: 204.2 | D17: 286.9 | E17: 379 | F17: =E17*(1+M30) -> 9044.3681 | L17: CA/CL | N17: =N5/N6 -> 1.0730668 | O17: =O5/O6 -> 1.017745
B18: Other | C18: 150.4 | D18: 202.89 | E18: 282 | F18: =E18*(1+M31) -> 2605.5713
B19: Total | C19: =SUM(C15:C18) -> 2224.9 | D19: =SUM(D15:D18) -> 2799.19 | E19: =SUM(E15:E18) -> 3601.89 | F19: =SUM(F15:F18) -> 22234.924 | L19: ROIC | O19: =R19/(O4+J6-J5) -> 0.72584009 | Q19: EBIT | R19: =Model!I12 -> -866.98696 | S19: =Model!R12/(1.1^9) -> 2779.9574
F20: =(F19/E19)^(1/10)-1 -> 0.19963885
B21: % US | C21: =C15/$C$19 -> 0.65886107 | D21: =D15/$D$19 -> 0.6444007 | E21: =E15/$E$19 -> 0.63336193
B22: % Other | C22: =1-C21 -> 0.34113893 | D22: =1-D21 -> 0.3555993 | E22: =1-E21 -> 0.36663807
B24: Growth | D24: =D15/C15-1 -> 0.23050686 | E24: =E15/D15-1 -> 0.26471893
B25: Growth | D25: =SUM(D16:D18)/SUM(C16:C18)-1 -> 0.31144928 | E25: =SUM(E16:E18)/SUM(D16:D18)-1 -> 0.32670612
C27: ABPDAU | D27: B | E27: DAU | G27: Pop | H27: Kids | I27: % MS | K27: eDAU | L27: eMS% | M27: Delta DAU
B28: NA | C28: =AVERAGE(45.03, 32.83, 34.36, 33.53, 46.56, 33.95, 34.36, 35.51, 47.79) -> 38.213333 | D28: =AVERAGE(599.9, 470.7, 487.6, 525.6, 727.7, 550.2, 587.6, 700.8) -> 581.2625 | E28: =D28/C28 -> 15.210987 | G28: 617 | H28: =G28*0.25 -> 154.25 | I28: =E28/H28 -> 0.098612555 | K28: =H28*$I$34 -> 55.089286 | L28: =K28/H28 -> 0.35714286 | M28: =K28/E28-1 -> 2.6216774
B29: Europe | C29: =AVERAGE(9.01, 7.76, 8.16, 8.38, 10.23, 8.44, 8.91, 9.9, 11.95) -> 9.1933333 | D29: =AVERAGE(149.5, 147.1, 148.3, 158.4, 204.4, 180.9, 183.8, 214.9) -> 173.4125 | E29: =D29/C29 -> 18.862854 | G29: 744 | H29: =G29*0.25 -> 186 | I29: =E29/H29 -> 0.10141319 | K29: =H29*$I$34 -> 66.428571 | L29: =K29/H29 -> 0.35714286 | M29: =K29/E29-1 -> 2.5216608
B30: APAC | C30: =AVERAGE(6.77, 6.19, 5.35, 5.24, 6.3, 5.67, 5, 5.21, 6.29) -> 5.78 | D30: =AVERAGE(92, 92.3, 82.7, 85.2, 108.4, 106.6, 100.9, 116.1, 140.3) -> 102.72222 | E30: =D30/C30 -> 17.772011 | G30: 4750 | H30: =G30*0.25 -> 1187.5 | I30: =E30/H30 -> 0.014965904 | K30: =H30*$I$34 -> 424.10714 | L30: =K30/H30 -> 0.35714286 | M30: =K30/E30-1 -> 22.863768
B31: Other | C31: =AVERAGE(3.79, 3.56, 3.51, 3.63, 4.61, 4.05, 3.84, 3.84, 4.51) -> 3.9266667 | D31: =AVERAGE(58.1, 63.7, 62.1, 70.3, 86.3, 86.1, 82.9, 96.7, 107.2) -> 79.266667 | E31: =D31/C31 -> 20.186757 | G31: =8200-SUM(G28:G30) -> 2089 | H31: =G31*0.25 -> 522.25 | I31: =E31/H31 -> 0.038653437 | K31: =H31*$I$34 -> 186.51786 | L31: =K31/H31 -> 0.35714286 | M31: =K31/E31-1 -> 8.2396146
B33: M | C33: T | D33: W | E33: T | F33: F | G33: S | H33: S | I33: DAU
B34: 0.25 | C34: 0.25 | D34: 0.25 | E34: 0.25 | F34: 0.5 | G34: 0.5 | H34: 0.5 | I34: =AVERAGE(B34:H34) -> 0.35714286

Sheet Model
A1: Main
C2: 2019 | D2: =C2+1 -> 2020 | E2: =D2+1 -> 2021 | F2: =E2+1 -> 2022 | G2: =F2+1 -> 2023 | H2: =G2+1 -> 2024 | I2: =H2+1 -> 2025 | J2: =I2+1 -> 2026 | K2: =J2+1 -> 2027 | ... R2: =Q2+1 -> 2034
B3: Revenue | F3: 2225 | G3: 2799.2 | H3: 3601.9 | I3: =H3*(1+Main!$F$20) -> 4320.9792 | J3: =I3*(1+Main!$F$20) -> 5183.6145 | K3: =J3*(1+Main!$F$20) -> 6218.4653 | L3: =K3*(1+Main!$F$20) -> 7459.9125 | M3: =L3*(1+Main!$F$20) -> 8949.2009 | N3: =M3*(1+Main!$F$20) -> 10735.809 | O3: =N3*(1+Main!$F$20) -> 12879.094 | P3: =O3*(1+Main!$F$20) -> 15450.261 | ... R3: =Q3*(1+Main!$F$20) -> 22234.986
B4: COGS | F4: 547.6 | G4: 649.1 | H4: 801.1 | I4: =I3*(H4/H3-0.005) -> 939.42578 | J4: =J3*(I4/I3-0.005) -> 1101.0536 | K4: =K3*(J4/J3-0.005) -> 1289.7743 | L4: =L3*(K4/K3-0.005) -> 1509.9638 | M4: =M3*(L4/L3-0.005) -> 1766.6653 | N4: =N3*(M4/M3-0.005) -> 2065.6812 | O4: =O3*(N4/N3-0.005) -> 2413.676 | P4: =P3*(O4/O3-0.005) -> 2818.2882 | ... R4: =R3*(Q4/Q3-0.005) -> 3833.5427
B5: Developer | F5: 623.8 | G5: 740.7 | H5: 922.8 | I5: =I3*(H5/H3-0.005) -> 1085.4218 | J5: =J3*(I5/I3-0.005) -> 1276.1961 | K5: =K3*(J5/J3-0.005) -> 1499.8821 | L5: =L3*(K5/K3-0.005) -> 1762.0173 | M5: =M3*(L5/L3-0.005) -> 2069.0384 | N5: =N3*(M5/M3-0.005) -> 2428.4198 | O5: =O3*(N5/N3-0.005) -> 2848.8312 | P5: =P3*(O5/O3-0.005) -> 3340.3173 | ... R5: =R3*(Q5/Q3-0.005) -> 4584.8122
B6: Infrastructure | F6: 689 | G6: 878.3 | H6: 915.4 | I6: =I3*(H6/H3-0.005) -> 1076.5445 | J6: =J3*(I6/I3-0.005) -> 1265.5465 | K6: =K3*(J6/J3-0.005) -> 1487.1065 | L6: =L3*(K6/K3-0.005) -> 1746.6911 | M6: =M3*(L6/L3-0.005) -> 2050.6525 | N6: =N3*(M6/M3-0.005) -> 2406.3634 | O6: =O3*(N6/N3-0.005) -> 2822.3715 | P6: =P3*(O6/O3-0.005) -> 3308.5752 | ... R6: =R3*(Q6/Q3-0.005) -> 4539.1311
B7: Gross Profit | F7: =F3-SUM(F4:F6) -> 364.6 | G7: =G3-SUM(G4:G6) -> 531.1 | H7: =H3-SUM(H4:H6) -> 962.6 | I7: =I3-SUM(I4:I6) -> 1219.587 | J7: =J3-SUM(J4:J6) -> 1540.8182 | K7: =K3-SUM(K4:K6) -> 1941.7024 | L7: =L3-SUM(L4:L6) -> 2441.2403 | M7: =M3-SUM(M4:M6) -> 3062.8447 | ... R7: =R3-SUM(R4:R6) -> 9277.4999
B8: R&D | F8: 873.4 | G8: 1253.59 | H8: 1444.2 | I8: =H8*1.03 -> 1487.526 | J8: =I8*1.03 -> 1532.1518 | K8: =J8*1.03 -> 1578.1163 | L8: =K8*1.03 -> 1625.4598 | M8: =L8*1.03 -> 1674.2236 | N8: =M8*1.03 -> 1724.4503 | O8: =N8*1.03 -> 1776.1838 | P8: =O8*1.03 -> 1829.4694 | ... R8: =Q8*1.03 -> 1940.884
B9: G&A | F9: 297.3 | G9: 390 | H9: 407.5 | I9: =H9*1.03 -> 419.725 | J9: =I9*1.03 -> 432.31675 | K9: =J9*1.03 -> 445.28625 | L9: =K9*1.03 -> 458.64484 | M9: =L9*1.03 -> 472.40419 | N9: =M9*1.03 -> 486.57631 | O9: =N9*1.03 -> 501.1736 | P9: =O9*1.03 -> 516.20881 | ... R9: =Q9*1.03 -> 547.64592
B10: S | F10: 117.4 | G10: 146.46 | H10: 174.1 | I10: =H10*1.03 -> 179.323 | J10: =I10*1.03 -> 184.70269 | K10: =J10*1.03 -> 190.24377 | L10: =K10*1.03 -> 195.95108 | M10: =L10*1.03 -> 201.82962 | N10: =M10*1.03 -> 207.8845 | O10: =N10*1.03 -> 214.12104 | P10: =O10*1.03 -> 220.54467 | ... R10: =Q10*1.03 -> 233.97584
B11: OpEx | C11: =SUM(C4:C10) -> 0 | D11: =SUM(D4:D10) -> 0 | E11: =SUM(E4:E10) -> 0 | F11: =SUM(F8:F10) -> 1288.1 | G11: =SUM(G8:G10) -> 1790.05 | H11: =SUM(H8:H10) -> 2025.8 | I11: =SUM(I8:I10) -> 2086.574 | J11: =SUM(J8:J10) -> 2149.1712 | K11: =SUM(K8:K10) -> 2213.6464 | L11: =SUM(L8:L10) -> 2280.0557 | M11: =SUM(M8:M10) -> 2348.4574 | ... R11: =SUM(R8:R10) -> 2722.5058
B12: OpInc | C12: =C3-C11 -> 0 | D12: =D3-D11 -> 0 | E12: =E3-E11 -> 0 | F12: =F7-F11 -> -923.5 | G12: =G7-G11 -> -1258.95 | H12: =H7-H11 -> -1063.2 | I12: =I7-I11 -> -866.98696 | J12: =J7-J11 -> -608.35301 | K12: =K7-K11 -> -271.944 | L12: =L7-L11 -> 161.18452 | M12: =M7-M11 -> 714.38725 | ... R12: =R7-R11 -> 6554.9941
B13: Interest | F13: 38.842 | G13: 141.8 | H13: 179.5
B14: Interest | F14: -39.903 | G14: -40.7 | H14: -41.1
B15: Other | F15: -5.74 | G15: -0.5 | H15: -11.5
B16: Pretax Income | C16: =SUM(C12:C15) -> 0 | D16: =SUM(D12:D15) -> 0 | E16: =SUM(E12:E15) -> 0 | F16: =SUM(F12:F15) -> -930.301 | G16: =SUM(G12:G15) -> -1158.35 | H16: =SUM(H12:H15) -> -936.3 | I16: =SUM(I12:I15) -> -866.98696 | J16: =SUM(J12:J15) -> -608.35301 | ... R16: =SUM(R12:R15) -> 6554.9941
B17: Tax | F17: 3.5 | G17: 0.4 | H17: 4.1 | I17: =I16*0.18 -> -156.05765 | J17: =J16*0.18 -> -109.50354 | K17: =K16*0.18 -> -48.949919 | L17: =L16*0.18 -> 29.013214 | M17: =M16*0.18 -> 128.58971 | N17: =N16*0.18 -> 254.95802 | O17: =O16*0.18 -> 414.49253 | P17: =P16*0.18 -> 615.03432 | ... R17: =R16*0.18 -> 1179.8989
B18: Net Income | C18: =C16-C17 -> 0 | D18: =D16-D17 -> 0 | E18: =E16-E17 -> 0 | F18: =F16-F17 -> -933.801 | G18: =G16-G17 -> -1158.75 | H18: =H16-H17 -> -940.4 | I18: =I16-I17 -> -710.92931 | J18: =J16-J17 -> -498.84947 | ... R18: =R16-R17 -> 5375.0952
B19: NCI | F19: -9.7 | G19: -6.9 | H19: -5.2
B20: Net Income | C20: =C18-C19 -> 0 | D20: =D18-D19 -> 0 | E20: =E18-E19 -> 0 | F20: =F18-F19 -> -924.101 | G20: =G18-G19 -> -1151.85 | H20: =H18-H19 -> -935.2 | I20: =I18-I19 -> -710.92931 | J20: =J18-J19 -> -498.84947 | ... R20: =R18-R19 -> 5375.0952 | S20: =R20*(1+$U$23) -> 5428.8461 | T20: =S20*(1+$U$23) -> 5483.1346 | U20: =T20*(1+$U$23) -> 5537.9659 | V20: =U20*(1+$U$23) -> 5593.3456 | W20: =V20*(1+$U$23) -> 5649.279 | X20: =W20*(1+$U$23) -> 5705.7718 | Y20: =X20*(1+$U$23) -> 5762.8295 | Z20: =Y20*(1+$U$23) -> 5820.4578 | ... GN20: =GM20*(1+$U$23) -> 31592.987
F21: =F8/F3 -> 0.39253933 | G21: =G8/G3 -> 0.44783867 | H21: =H8/H3 -> 0.40095505
B23: Revenue Growth | G23: =G3/F3-1 -> 0.25806742 | H23: =H3/G3-1 -> 0.2867605 | I23: =I3/H3-1 -> 0.19963885 | J23: =J3/I3-1 -> 0.19963885 | K23: =K3/J3-1 -> 0.19963885 | L23: =L3/K3-1 -> 0.19963885 | M23: =M3/L3-1 -> 0.19963885 | N23: =N3/M3-1 -> 0.19963885 | ... R23: =R3/Q3-1 -> 0.19963885 | T23: Maturity | U23: 0.01
B24: Gross Margin | F24: =F7/F3 -> 0.16386517 | G24: =G7/G3 -> 0.18973278 | H24: =H7/H3 -> 0.26724784 | I24: =I7/I3 -> 0.28224784 | J24: =J7/J3 -> 0.29724784 | K24: =K7/K3 -> 0.31224784 | L24: =L7/L3 -> 0.32724784 | M24: =M7/M3 -> 0.34224784 | ... R24: =R7/R3 -> 0.41724784 | T24: Discount | U24: 0.1
B25: Op Margin | F25: =F12/F3 -> -0.41505618 | G25: =G12/G3 -> -0.4497535 | H25: =H12/H3 -> -0.29517755 | I25: =I12/I3 -> -0.20064595 | J25: =J12/J3 -> -0.11736077 | K25: =K12/K3 -> -0.04373169 | L25: =L12/L3 -> 0.021606758 | M25: =M12/M3 -> 0.079826933 | ... R25: =R12/R3 -> 0.29480541 | T25: NPV | U25: =NPV(U24,I20:GN20)+Main!J5-Main!J6 -> 30565.057
T26: Price | U26: =U25/Main!J3 -> 45.804072
T27: Difference | U27: =U26/Main!J2-1 -> -0.65035059
E28: 1 | F28: =E28+1 -> 2 | G28: =F28+1 -> 3 | H28: =G28+1 -> 4 | I28: =H28+1 -> 5 | J28: =I28+1 -> 6 | K28: =J28+1 -> 7 | L28: =K28+1 -> 8 | M28: =L28+1 -> 9 | N28: =M28+1 -> 10
D29: 100 | E29: =D29*1.01 -> 101 | F29: =E29*1.01 -> 102.01 | G29: =F29*1.01 -> 103.0301 | H29: =G29*1.01 -> 104.0604 | I29: =H29*1.01 -> 105.10101 | J29: =I29*1.01 -> 106.15202 | K29: =J29*1.01 -> 107.21354 | L29: =K29*1.01 -> 108.28567 | ... N29: =M29*1.01 -> 110.46221
D30: =D29*0.5 -> 50 | E30: =E29*(D30/D29+0.01) -> 51.51 | F30: =F29*(E30/E29+0.01) -> 53.0452 | G30: =G29*(F30/F29+0.01) -> 54.605953 | H30: =H29*(G30/G29+0.01) -> 56.192617 | I30: =I29*(H30/H29+0.01) -> 57.805553 | J30: =J29*(I30/I29+0.01) -> 59.445128 | K30: =K29*(J30/J29+0.01) -> 61.111715 | L30: =L29*(K30/K29+0.01) -> 62.805689 | ... N30: =N29*(M30/M29+0.01) -> 66.277328
K32: -0.42 | L32: -0.45 | M32: -0.09 | N32: -0.1
M34: =N34/10 -> 0.001 | N34: =MAX(D32:N32)-N32 -> 0.01
